pyppl_export.py
pyppl_export-0.0.6.dist-info/entry_points.txt
pyppl_export-0.0.6.dist-info/LICENSE
pyppl_export-0.0.6.dist-info/WHEEL
pyppl_export-0.0.6.dist-info/METADATA
pyppl_export-0.0.6.dist-info/RECORD
